configmount
