Metadata-Version: 2.1
Name: configmount
Version: 0.0.27rc1
Summary: Configmount mounts directories containing configuration files (augtools compatible files, yaml-files) as directories, so that every configuration value is accessible as file.
Home-page: https://gitlab.com/domsonAut/configmount
Author: Dominik Kummer
Author-email: admin@arkades.org
License: UNKNOWN
Project-URL: Bug Reports, https://gitlab.com/domsonAut/configmount/issues
Project-URL: Source, https://gitlab.com/domsonAut/configmount/
Keywords: filesystem oriented configuration management
Platform: UNKNOWN
Classifier: Development Status :: 3 - Alpha
Classifier: Intended Audience :: System Administrators
Classifier: Topic :: System :: Systems Administration
Classifier: License :: OSI Approved :: GNU General Public License v3 (GPLv3)
Classifier: Programming Language :: Python :: 3.7
Requires-Python: >=3
